setup.cfg
setup.py
screenshotmonitor/__init__.py
screenshotmonitor/api_object.py
screenshotmonitor/exc.py
screenshotmonitor/objects.py
screenshotmonitor/screenshot_monitor.py
screenshotmonitor/util.py
screenshotmonitor_py.egg-info/PKG-INFO
screenshotmonitor_py.egg-info/SOURCES.txt
screenshotmonitor_py.egg-info/dependency_links.txt
screenshotmonitor_py.egg-info/requires.txt
screenshotmonitor_py.egg-info/top_level.txt