Metadata-Version: 1.1
Name: screenshotmonitor-py
Version: 0.1.0
Summary: Unofficial library for using v2 of the ScreenshotMonitor.com API
Home-page: https://bitbucket.org/phistrom/screenshotmonitor_py
Author: Phillip Stromberg
Author-email: phillip@stromberg.me
License: Apache
Download-URL: https://bitbucket.org/phistrom/screenshotmonitor_py/get/v0.1.0.zip
Platform: UNKNOWN
Classifier: Development Status :: 4 - Beta
Classifier: License :: OSI Approved :: Apache Software License
Classifier: Operating System :: OS Independent
Classifier: Programming Language :: Python
Classifier: Programming Language :: Python :: 2.7
Classifier: Programming Language :: Python :: 3
Classifier: Programming Language :: Python :: 3.3
Classifier: Programming Language :: Python :: 3.4
Classifier: Programming Language :: Python :: 3.5
Classifier: Topic :: Internet
